jin2cli-0.2.dist-info/metadata.json
jin2cli-0.2.dist-info/RECORD
jin2cli-0.2.dist-info/DESCRIPTION.rst
jin2cli-0.2.dist-info/entry_points.txt
jin2cli-0.2.dist-info/METADATA
jin2cli-0.2.dist-info/WHEEL
jin2cli-0.2.dist-info/top_level.txt
jin2cli/exceptions.py
jin2cli/cli.py
jin2cli/__init__.py
j2cli/__init__.py
