Metadata-Version: 2.0
Name: jin2cli
Version: 0.2
Summary: json + jinja2 template == file
Home-page: https://github.com/tommyvn/jin2cli
Author: Tom van Neerijnen
Author-email: tom@tomvn.com
License: Apache
Keywords: cli jinja2 template
Platform: UNKNOWN
Classifier: Development Status :: 5 - Production/Stable
Classifier: Intended Audience :: Developers
Classifier: License :: OSI Approved :: Apache Software License
Classifier: Programming Language :: Python :: 2.7
Requires-Dist: jinja2
